oxyparser/__init__.py
oxyparser/ai/__init__.py
oxyparser/ai/query.py
oxyparser/cache/__init__.py
oxyparser/cache/base.py
oxyparser/cache/file.py
oxyparser/cache/redis.py
oxyparser/cache/utils.py
oxyparser/exceptions.py
oxyparser/logging.py
oxyparser/models.py
oxyparser/oxyparser.py
oxyparser/parser/__init__.py
oxyparser/parser/ai_parser.py
oxyparser/parser/cleaner.py
oxyparser/parser/parser.py
oxyparser/scraper/__init__.py
oxyparser/scraper/scraper.py
oxyparser/scripts.py
oxyparser/settings.py
oxyparser/utils.py
oxyparser-0.1.0.dist-info/LICENSE
oxyparser-0.1.0.dist-info/METADATA
oxyparser-0.1.0.dist-info/WHEEL
oxyparser-0.1.0.dist-info/entry_points.txt
oxyparser-0.1.0.dist-info/RECORD
