Metadata-Version: 2.1
Name: oxyparser
Version: 0.1.0
Summary: 
Author: Tadas Gedgaudas
Author-email: tadasgedgaudas@oxylabs.io
Requires-Python: >=3.8,<4.0
Classifier: Programming Language :: Python :: 3
Classifier: Programming Language :: Python :: 3.8
Classifier: Programming Language :: Python :: 3.9
Classifier: Programming Language :: Python :: 3.10
Classifier: Programming Language :: Python :: 3.11
Classifier: Programming Language :: Python :: 3.12
Requires-Dist: aiofiles (>=23.2.1,<24.0.0)
Requires-Dist: isort (>=5.13.2,<6.0.0)
Requires-Dist: litellm (>=1.30.5,<2.0.0)
Requires-Dist: lxml (>=5.1.0,<6.0.0)
Requires-Dist: pydantic (>=2.6.3,<3.0.0)
Requires-Dist: pydantic-settings (>=2.2.1,<3.0.0)
Requires-Dist: redis (>=5.0.2,<6.0.0)
Requires-Dist: structlog (>=24.1.0,<25.0.0)
Requires-Dist: tenacity (>=8.2.3,<9.0.0)
Requires-Dist: tiktoken (>=0.6.0,<0.7.0)
Requires-Dist: tldextract (>=5.1.1,<6.0.0)
Requires-Dist: types-aiofiles (>=23.2.0.20240106,<24.0.0.0)
